tda_mapper-0.12.0.dist-info/licenses/LICENSE
tdamapper/__init__.py
tdamapper/_common.py
tdamapper/_run_app.py
tdamapper/app.py
tdamapper/clustering.py
tdamapper/core.py
tdamapper/cover.py
tdamapper/learn.py
tdamapper/plot.py
tdamapper/plot_backends/__init__.py
tdamapper/plot_backends/plot_matplotlib.py
tdamapper/plot_backends/plot_plotly.py
tdamapper/plot_backends/plot_pyvis.py
tdamapper/utils/__init__.py
tdamapper/utils/_metrics.py
tdamapper/utils/heap.py
tdamapper/utils/metrics.py
tdamapper/utils/quickselect.py
tdamapper/utils/unionfind.py
tdamapper/utils/vptree.py
tdamapper/utils/vptree_flat/__init__.py
tdamapper/utils/vptree_flat/ball_search.py
tdamapper/utils/vptree_flat/builder.py
tdamapper/utils/vptree_flat/common.py
tdamapper/utils/vptree_flat/knn_search.py
tdamapper/utils/vptree_flat/vptree.py
tdamapper/utils/vptree_hier/__init__.py
tdamapper/utils/vptree_hier/ball_search.py
tdamapper/utils/vptree_hier/builder.py
tdamapper/utils/vptree_hier/common.py
tdamapper/utils/vptree_hier/knn_search.py
tdamapper/utils/vptree_hier/vptree.py
tda_mapper-0.12.0.dist-info/METADATA
tda_mapper-0.12.0.dist-info/WHEEL
tda_mapper-0.12.0.dist-info/entry_points.txt
tda_mapper-0.12.0.dist-info/top_level.txt
tda_mapper-0.12.0.dist-info/RECORD
