Metadata-Version: 2.4
Name: tda-mapper
Version: 0.12.0
Summary: A simple and efficient Python implementation of Mapper algorithm for Topological Data Analysis
Author-email: Luca Simi <lucasimi90@gmail.com>
Maintainer-email: Luca Simi <lucasimi90@gmail.com>
License:                                  Apache License
Project-URL: Homepage, https://github.com/lucasimi/tda-mapper-python
Project-URL: Documentation, https://tda-mapper.readthedocs.io
Project-URL: Issues, https://github.com/lucasimi/tda-mapper-python/issues
Keywords: tda,mapper,topology,topological data analysis
Classifier: Intended Audience :: Developers
Classifier: Intended Audience :: Science/Research
Classifier: Topic :: Scientific/Engineering :: Mathematics
Classifier: Topic :: Scientific/Engineering :: Information Analysis
Classifier: Topic :: Scientific/Engineering :: Visualization
Classifier: Topic :: Software Development :: Libraries
Classifier: License :: OSI Approved :: Apache Software License
Classifier: Programming Language :: Python
Classifier: Programming Language :: Python :: 3
Classifier: Programming Language :: Python :: 3.8
Classifier: Programming Language :: Python :: 3.9
Classifier: Programming Language :: Python :: 3.10
Classifier: Programming Language :: Python :: 3.11
Classifier: Programming Language :: Python :: 3.12
Classifier: Programming Language :: Python :: 3.13
Classifier: Operating System :: OS Independent
Requires-Python: >=3.8
License-File: LICENSE
Requires-Dist: numpy<2.0.0,>=1.20.1
Requires-Dist: matplotlib<4.0.0,>=3.3.4
Requires-Dist: networkx<3.0.0,>=2.5
Requires-Dist: igraph<0.12.0,>=0.11.8
Requires-Dist: numba<0.62,>=0.54
Requires-Dist: pyvis<0.4.0,>=0.3.2
Requires-Dist: plotly<7.0.0,>=6.0.1
Requires-Dist: joblib<2.0.0,>=1.4.2
Provides-Extra: dev
Requires-Dist: coverage[toml]; extra == "dev"
Requires-Dist: pandas<3.0.0; extra == "dev"
Requires-Dist: scikit-learn<1.6.0; extra == "dev"
Requires-Dist: pytest; extra == "dev"
Requires-Dist: pytest-asyncio; extra == "dev"
Requires-Dist: black[jupyter]; extra == "dev"
Requires-Dist: isort; extra == "dev"
Requires-Dist: flake8; extra == "dev"
Requires-Dist: kaleido; extra == "dev"
Requires-Dist: nbformat>=4.2.0; extra == "dev"
Provides-Extra: app
Requires-Dist: pandas<3.0.0; extra == "app"
Requires-Dist: scikit-learn<1.6.0; extra == "app"
Requires-Dist: umap-learn<0.6.0; extra == "app"
Requires-Dist: nicegui<3.0.0,>=2.18.0; extra == "app"
Dynamic: license-file
